string_templates/__init__.py
string_templates-0.1.1.dist-info/WHEEL
string_templates-0.1.1.dist-info/METADATA
string_templates-0.1.1.dist-info/RECORD
