Metadata-Version: 2.1
Name: string-templates
Version: 0.1.1
Summary: simple string template library
Home-page: https://github.com/JulianSobott/string_templates
Keywords: template
Author: JulianSobott
Author-email: julian.sobott@gmail.com
Requires-Python: >=3.7,<4.0
Classifier: Programming Language :: Python :: 3
Classifier: Programming Language :: Python :: 3.7
Classifier: Programming Language :: Python :: 3.8
Classifier: Programming Language :: Python :: 3.9
Project-URL: Repository, https://github.com/JulianSobott/string_templates
